{
  "obsidian-outliner:indent-list": [
    {
      "modifiers": [
        "Ctrl",
        "Mod"
      ],
      "key": "ArrowRight"
    }
  ],
  "obsidian-outliner:move-list-item-down": [
    {
      "modifiers": [
        "Ctrl",
        "Mod"
      ],
      "key": "ArrowDown"
    }
  ],
  "obsidian-outliner:move-list-item-up": [
    {
      "modifiers": [
        "Ctrl",
        "Mod"
      ],
      "key": "ArrowUp"
    }
  ],
  "obsidian-outliner:outdent-list": [
    {
      "modifiers": [
        "Ctrl",
        "Mod"
      ],
      "key": "ArrowLeft"
    }
  ],
  "obsidian-outliner:unfold": [],
  "obsidian-outliner:system-info": [],
  "obsidian-outliner:fold": [],
  "obsidian-plugin-toc:create-toc": [
    {
      "modifiers": [
        "Ctrl",
        "Mod"
      ],
      "key": "T"
    }
  ]
}